myanmar/__init__.py
myanmar/_landlines.py
myanmar/converter.py
myanmar/encodings.py
myanmar/language.py
myanmar/nrc.py
myanmar/phonenumber.py
myanmar/data/bgn-pcgn.json
myanmar/data/ipa.json
myanmar/data/mlc.json
myanmar/data/nrc_townships.json
myanmar/data/unicode.json
myanmar/data/wininnwa.json
myanmar/data/zawgyi.json
python_myanmar-1.10.0.dist-info/AUTHORS.rst
python_myanmar-1.10.0.dist-info/LICENSE
python_myanmar-1.10.0.dist-info/METADATA
python_myanmar-1.10.0.dist-info/WHEEL
python_myanmar-1.10.0.dist-info/top_level.txt
python_myanmar-1.10.0.dist-info/RECORD
