Metadata-Version: 2.1
Name: python-myanmar
Version: 1.10.0
Summary: Various Python Routines for Myanmar Language
Home-page: https://github.com/trhura/python-myanmar
Author: Thura Hlaing
Author-email: trhura@gmail.com
License: MIT license
Keywords: python-myanmar
Platform: UNKNOWN
Classifier: Development Status :: 2 - Pre-Alpha
Classifier: Intended Audience :: Developers
Classifier: License :: OSI Approved :: MIT License
Classifier: Natural Language :: English
Classifier: Programming Language :: Python :: 3
Classifier: Programming Language :: Python :: 3.4
Classifier: Programming Language :: Python :: 3.5
Classifier: Programming Language :: Python :: 3.6
